MANIFEST.in
README.md
setup.py
dash_katex/DashKatex.py
dash_katex/__init__.py
dash_katex/_imports_.py
dash_katex/dash_katex.dev.js
dash_katex/dash_katex.min.js
dash_katex/metadata.json
dash_katex/package.json
dash_katex.egg-info/PKG-INFO
dash_katex.egg-info/SOURCES.txt
dash_katex.egg-info/dependency_links.txt
dash_katex.egg-info/top_level.txt