Metadata-Version: 1.0
Name: dash-katex
Version: 0.0.1
Summary: Katex in Dash
Home-page: UNKNOWN
Author: xhlulu xinghan@plot.ly
Author-email: UNKNOWN
License: MIT
Platform: UNKNOWN
